melee_20XX/Melee_v0.py
melee_20XX/__init__.py
20XX-0.1.2.dist-info/LICENSE.txt
20XX-0.1.2.dist-info/METADATA
20XX-0.1.2.dist-info/WHEEL
20XX-0.1.2.dist-info/top_level.txt
20XX-0.1.2.dist-info/RECORD
