Metadata-Version: 2.1
Name: 20XX
Version: 0.1.2
Summary: =?utf-8?b?MjBYWCBpcyBhIFBldHRpbmdab28tYmFzZWQgbGlicmFyeSBmb3IgTWVsZWUuICjijJDilqBf4pagKQ==?=
Home-page: https://github.com/WillDudley/20XX
Author: Will Dudley
Author-email: will2346@live.co.uk
Project-URL: Bug Tracker, https://https://github.com/WillDudley/20XX/issues
Classifier: Programming Language :: Python :: 3
Classifier: Development Status :: 4 - Beta
Classifier: Natural Language :: English
Classifier: License :: OSI Approved :: GNU Lesser General Public License v3 (LGPLv3)
Classifier: Operating System :: POSIX :: Linux
Requires-Python: >=3.6
License-File: LICENSE.txt
Requires-Dist: libmelee
Requires-Dist: requests (>=2.20)
Requires-Dist: tqdm (>=4.14)
Requires-Dist: pettingzoo (>=1.12.1)
